LICENSE
README.md
pyproject.toml
setup.py
power_perceiver/__init__.py
power_perceiver/consts.py
power_perceiver/exceptions.py
power_perceiver/geospatial.py
power_perceiver/hub.py
power_perceiver/testing.py
power_perceiver/time.py
power_perceiver/utils.py
power_perceiver.egg-info/PKG-INFO
power_perceiver.egg-info/SOURCES.txt
power_perceiver.egg-info/dependency_links.txt
power_perceiver.egg-info/requires.txt
power_perceiver.egg-info/top_level.txt
power_perceiver/analysis/__init__.py
power_perceiver/analysis/log_national_pv.py
power_perceiver/analysis/plot_probability_timeseries.py
power_perceiver/analysis/plot_satellite.py
power_perceiver/analysis/plot_timeseries.py
power_perceiver/analysis/plot_tsne.py
power_perceiver/analysis/simple_callback.py
power_perceiver/experiments/__init__.py
power_perceiver/experiments/demo_of_new_proposed_architecture.py
power_perceiver/experiments/exp_008_perceiver_IO.py
power_perceiver/experiments/exp_009_perceiver_IO_include_decoder_query_in_encoder_query.py
power_perceiver/experiments/exp_010_perceiver_IO_include_decoder_query_in_encoder_query_using_neural_net.py
power_perceiver/experiments/exp_011_perceiver_IO_include_decoder_query_in_encoder_query_using_neural_net.py
power_perceiver/experiments/exp_012_perceiver_IO_include_decoder_query_in_encoder_query_using_neural_net.py
power_perceiver/experiments/exp_013_perceiver_IO_include_decoder_query_in_encoder_query_using_neural_net.py
power_perceiver/experiments/exp_014_back_to_transformer_encoder.py
power_perceiver/experiments/exp_015_multiple_timesteps_of_satellite_imagery.py
power_perceiver/experiments/exp_016_predict_satellite_imagery.py
power_perceiver/experiments/exp_017_infer_individual_pv_power.py
power_perceiver/experiments/exp_018_infer_GSP_and_individual_pv_power.py
power_perceiver/experiments/exp_019_transformer_over_time.py
power_perceiver/experiments/exp_020_transformer_over_time_without_for_loops.py
power_perceiver/experiments/exp_021_predict_future_imagery_climatehack.py
power_perceiver/experiments/exp_022_predict_future_imagery_climatehack_train_from_zarr.py
power_perceiver/experiments/exp_023_unet_and_power_perceiver.py
