Metadata-Version: 2.1
Name: power-perceiver
Version: 2022.9.6
Summary: Machine learning experiments to forecast the electricity system (starting with solar)
Author: Jack Kelly
License: MIT License
Classifier: Development Status :: 4 - Beta
Classifier: Intended Audience :: Developers
Classifier: Topic :: Scientific/Engineering :: Artificial Intelligence
Classifier: License :: OSI Approved :: MIT License
Classifier: Programming Language :: Python :: 3.10
Requires-Python: >=3.10
Provides-Extra: develop
Provides-Extra: train
License-File: LICENSE
